django_admin_daterange_listfilter/.DS_Store
django_admin_daterange_listfilter/__init__.py
django_admin_daterange_listfilter/admin.py
django_admin_daterange_listfilter/apps.py
django_admin_daterange_listfilter/filters.py
django_admin_daterange_listfilter/models.py
django_admin_daterange_listfilter/tests.py
django_admin_daterange_listfilter/views.py
django_admin_daterange_listfilter/locale/zh_Hans/LC_MESSAGES/django.mo
django_admin_daterange_listfilter/locale/zh_Hans/LC_MESSAGES/django.po
django_admin_daterange_listfilter/migrations/__init__.py
django_admin_daterange_listfilter/static/.DS_Store
django_admin_daterange_listfilter/static/django_admin_daterange_listfilter/.DS_Store
django_admin_daterange_listfilter/static/django_admin_daterange_listfilter/css/DateRangeFilter.css
django_admin_daterange_listfilter/static/django_admin_daterange_listfilter/js/DateRangeFilter.js
django_admin_daterange_listfilter/static/django_admin_daterange_listfilter/js/parseParam.js
django_admin_daterange_listfilter/templates/django_admin_daterange_listfilter/filters/DateRangeFilter.html
django_admin_daterange_listfilter-0.1.6.dist-info/licenses/LICENSE
django_admin_daterange_listfilter-0.1.6.dist-info/METADATA
django_admin_daterange_listfilter-0.1.6.dist-info/WHEEL
django_admin_daterange_listfilter-0.1.6.dist-info/top_level.txt
django_admin_daterange_listfilter-0.1.6.dist-info/RECORD
