Metadata-Version: 2.4
Name: django-admin-daterange-listfilter
Version: 0.1.6
Summary: 为Django模型列表页的时间过滤器增加日期范围选择功能。
Author: Zhan YuCong
Maintainer: Zhan YuCong
License: MIT
Keywords: django admin extentions,daterange listfilter
Classifier: Development Status :: 5 - Production/Stable
Classifier: Intended Audience :: Developers
Classifier: Topic :: Software Development :: Libraries :: Python Modules
Classifier: License :: OSI Approved :: MIT License
Classifier: Programming Language :: Python :: 3
Classifier: Programming Language :: Python :: 3 :: Only
License-File: LICENSE
Requires-Dist: django
Requires-Dist: django-static-jquery-ui
Requires-Dist: django-middleware-global-request
Requires-Dist: django-listfilter-media-extension
Dynamic: author
Dynamic: classifier
Dynamic: description
Dynamic: description-content-type
Dynamic: keywords
Dynamic: license
Dynamic: license-file
Dynamic: maintainer
Dynamic: requires-dist
Dynamic: summary
